data_partitioner/__init__.py
data_partitioner/data_suplier.py
data_partitioner/partitioner.py
data_partitioner-0.1.dist-info/DESCRIPTION.rst
data_partitioner-0.1.dist-info/METADATA
data_partitioner-0.1.dist-info/RECORD
data_partitioner-0.1.dist-info/WHEEL
data_partitioner-0.1.dist-info/metadata.json
data_partitioner-0.1.dist-info/top_level.txt
