Metadata-Version: 2.0
Name: data-partitioner
Version: 0.1
Summary: Consistently partitions a dataset into a training set and a test set
Home-page: https://github.com/brahle/data_partitioner
Author: brahle
Author-email: brahle@gmail.com
License: GNU Lesser General Public License (LGPL), Version 3
Platform: UNKNOWN
Classifier: Development Status :: 4 - Beta
Classifier: Intended Audience :: Developers
Classifier: Intended Audience :: Education
Classifier: Intended Audience :: Information Technology
Classifier: Intended Audience :: Science/Research
Classifier: License :: OSI Approved :: GNU Lesser General Public License v3 or later (LGPLv3+)
Classifier: Operating System :: OS Independent
Classifier: Programming Language :: Python :: 3
Classifier: Topic :: Software Development :: Libraries :: Python Modules
